d4train/dp.py
d4train-0.0.2.2.dist-info/LICENSE
d4train-0.0.2.2.dist-info/METADATA
d4train-0.0.2.2.dist-info/WHEEL
d4train-0.0.2.2.dist-info/top_level.txt
d4train-0.0.2.2.dist-info/RECORD
