Metadata-Version: 2.1
Name: d4train
Version: 0.0.2.2
Summary: prepare your dataset for finetuning LLMs
Author: Shuvam Mandal
Author-email: shuvammandal121@gmail.com
License-File: LICENSE
Requires-Dist: datasets
Requires-Dist: transformers
Requires-Dist: pandas
